productdb/__init__.py
productdb/_version.py
productdb-0.0.4.dist-info/LICENSE
productdb-0.0.4.dist-info/METADATA
productdb-0.0.4.dist-info/WHEEL
productdb-0.0.4.dist-info/top_level.txt
productdb-0.0.4.dist-info/RECORD
